<?xml version="1.0" encoding="utf-8" standalone="no"?>
<?xml-stylesheet type="text/xsl" href="gesture_data.xsl"?>
<!DOCTYPE gestures SYSTEM "gesture_data.dtd">
<gestures>
	<gesture>
		<hand side="left">
			<thumb>
				<flex>0</flex>
				<contact-tip>false</contact-tip>
			</thumb>
			<index>
				<flex>0</flex>
				<contact-tip>false</contact-tip>
				<contact-mid>false</contact-mid>
			</index>
			<middle>
				<flex>0</flex>
				<contact-tip>false</contact-tip>
				<contact-mid>false</contact-mid>
			</middle>
			<ring>
				<flex>0</flex>
				<contact-tip>false</contact-tip>
				<contact-mid>false</contact-mid>
			</ring>
			<pinky>
				<flex>0</flex>
				<contact-tip>false</contact-tip>
				<contact-mid>false</contact-mid>
			</pinky>
			<thumb-index>
				<contact-tip>false</contact-tip>
			</thumb-index>
			<index-middle>
				<contact-tip>false</contact-tip>
			</index-middle>
			<middle-ring>
				<contact-tip>false</contact-tip>
			</middle-ring>
			<ring-pinky>
				<contact-tip>false</contact-tip>
			</ring-pinky>
			<lsm303 side="top">
				<accel-x>0</accel-x>
				<accel-y>0</accel-y>
				<accel-z>0</accel-z>
				<mag-x>0</mag-x>
				<mag-y>0</mag-y>
				<mag-z>0</mag-z>
			</lsm303>
			<lsm303 side="bottom">
				<accel-x>0</accel-x>
				<accel-y>0</accel-y>
				<accel-z>0</accel-z>
				<mag-x>0</mag-x>
				<mag-y>0</mag-y>
				<mag-z>0</mag-z>
			</lsm303>
			<lsm9dof side="top">
				<accel-x>0</accel-x>
				<accel-y>0</accel-y>
				<accel-z>0</accel-z>
				<mag-x>0</mag-x>
				<mag-y>0</mag-y>
				<mag-z>0</mag-z>
				<gyro-x>0</gyro-x>
				<gyro-y>0</gyro-y>
				<gyro-z>0</gyro-z>
			</lsm9dof>
			<lsm9dof side="bottom">
				<accel-x>0</accel-x>
				<accel-y>0</accel-y>
				<accel-z>0</accel-z>
				<mag-x>0</mag-x>
				<mag-y>0</mag-y>
				<mag-z>0</mag-z>
				<gyro-x>0</gyro-x>
				<gyro-y>0</gyro-y>
				<gyro-z>0</gyro-z>
			</lsm9dof>
		</hand>
		<hand side="right">
			<thumb>
				<flex>0</flex>
				<contact-tip>false</contact-tip>
			</thumb>
			<index>
				<flex>65</flex>
				<contact-tip>false</contact-tip>
				<contact-mid>false</contact-mid>
			</index>
			<middle>
				<flex>75</flex>
				<contact-tip>false</contact-tip>
				<contact-mid>false</contact-mid>
			</middle>
			<ring>
				<flex>85</flex>
				<contact-tip>false</contact-tip>
				<contact-mid>false</contact-mid>
			</ring>
			<pinky>
				<flex>0</flex>
				<contact-tip>false</contact-tip>
				<contact-mid>false</contact-mid>
			</pinky>
			<thumb-index>
				<contact-tip>false</contact-tip>
			</thumb-index>
			<index-middle>
				<contact-tip>false</contact-tip>
			</index-middle>
			<middle-ring>
				<contact-tip>true</contact-tip>
			</middle-ring>
			<ring-pinky>
				<contact-tip>false</contact-tip>
			</ring-pinky>
			<lsm303 side="top">
				<accel-x>-1012</accel-x>
				<accel-y>-36</accel-y>
				<accel-z>208</accel-z>
				<mag-x>499</mag-x>
				<mag-y>167</mag-y>
				<mag-z>-39</mag-z>
			</lsm303>
			<lsm303 side="bottom">
				<accel-x>-912</accel-x>
				<accel-y>120</accel-y>
				<accel-z>264</accel-z>
				<mag-x>611</mag-x>
				<mag-y>113</mag-y>
				<mag-z>204</mag-z>
			</lsm303>
			<lsm9dof side="top">
				<accel-x>-17505</accel-x>
				<accel-y>-2455</accel-y>
				<accel-z>1859</accel-z>
				<mag-x>3585</mag-x>
				<mag-y>8952</mag-y>
				<mag-z>-627</mag-z>
				<gyro-x>85</gyro-x>
				<gyro-y>415</gyro-y>
				<gyro-z>-242</gyro-z>
			</lsm9dof>
			<lsm9dof side="bottom">
				<accel-x>-15759</accel-x>
				<accel-y>-3338</accel-y>
				<accel-z>7561</accel-z>
				<mag-x>5190</mag-x>
				<mag-y>8569</mag-y>
				<mag-z>-275</mag-z>
				<gyro-x>49</gyro-x>
				<gyro-y>40</gyro-y>
				<gyro-z>-461</gyro-z>
			</lsm9dof>
		</hand>
	</gesture>
		<converted-text></converted-text>
	<status>connected</status>
	<version>1.0</version>
</gestures>
